lightpush/__init__.py
lightpush-0.1.3.dist-info/METADATA
lightpush-0.1.3.dist-info/RECORD
lightpush-0.1.3.dist-info/WHEEL
lightpush-0.1.3.dist-info/top_level.txt
