Metadata-Version: 2.1
Name: lightpush
Version: 0.1.3
Summary: A Simple package for ServerChan
Home-page: http://github.com/anhenghuang/lightpush
Author: anhenghuang
Author-email: contact@anhenghuang.com
License: MIT
Platform: UNKNOWN
Classifier: Programming Language :: Python :: 3
Classifier: License :: OSI Approved :: MIT License
Classifier: Operating System :: OS Independent
Requires-Dist: requests
